<?xml version = '1.0' encoding = 'UTF-8'?>
<TableProxyOraclev11g class="oracle.dbtools.crest.model.design.storage.oracle.v11g.TableProxyOraclev11g" name="TA_CTA_FRE_DAZ" directorySegmentName="seg_1" id="999AA2DF-458B-42FE-D20B-62419B7B2A5C">
<createdBy>lpedrero</createdBy>
<createdTime>2020-01-29 17:50:08 UTC</createdTime>
<ownerDesignName>diagrama</ownerDesignName>
<schemaObject>8AD07257-1A3E-3202-6080-D8F43B2E5CBC</schemaObject>
<logging>YES</logging>
<partitionedRowMovement>DISABLE</partitionedRowMovement>
<segment>E030A1CF-5AD1-76F4-1539-3E7D684F206E</segment>
<tableSpace>C5F77C84-5A7C-678B-F436-B61966C09F06</tableSpace>
<temporaryChanged>false</temporaryChanged>
<accessDriverType>oracle_loader</accessDriverType>
<rejectLimit></rejectLimit>
<columnProxies itemClass="oracle.dbtools.crest.model.design.storage.oracle.v12c.ColumnProxyOraclev12c">
<ColumnProxy name="FI_ACTIVO_CNBV" id="03D3DD33-EB62-24C6-C5C4-499AD3DDD6E6">
<createdBy>lpedrero</createdBy>
<createdTime>2020-01-29 17:50:08 UTC</createdTime>
<ownerDesignName>diagrama</ownerDesignName>
</ColumnProxy>
<ColumnProxy name="FI_STATUS" id="16C87B5C-5AAA-5C91-17E0-BF6A220FE083">
<createdBy>lpedrero</createdBy>
<createdTime>2020-01-29 17:50:08 UTC</createdTime>
<ownerDesignName>diagrama</ownerDesignName>
</ColumnProxy>
<ColumnProxy name="FC_USUARIO_MODIFICO" id="211F73E3-09C4-4D2E-509D-D6BF464814FB">
<createdBy>lpedrero</createdBy>
<createdTime>2020-01-29 17:50:08 UTC</createdTime>
<ownerDesignName>diagrama</ownerDesignName>
</ColumnProxy>
<ColumnProxy name="FD_FECHA_ALTA" id="23F8EDCE-EB2C-C37F-4FA6-7F57AAEB08E5">
<createdBy>lpedrero</createdBy>
<createdTime>2020-01-29 17:50:08 UTC</createdTime>
<ownerDesignName>diagrama</ownerDesignName>
</ColumnProxy>
<ColumnProxy name="FI_ID_ALNOVA" id="2D7CEF12-4480-3924-8E81-39AEB161B38A">
<createdBy>lpedrero</createdBy>
<createdTime>2020-01-29 17:50:08 UTC</createdTime>
<ownerDesignName>diagrama</ownerDesignName>
</ColumnProxy>
<ColumnProxy name="FC_USUARIO_ALTA" id="358D85BB-00BE-B9CE-C877-1AEB1D70BEDB">
<createdBy>lpedrero</createdBy>
<createdTime>2020-01-29 17:50:08 UTC</createdTime>
<ownerDesignName>diagrama</ownerDesignName>
</ColumnProxy>
<ColumnProxy name="FI_ID_VERSION" id="4946730E-2A1F-3C91-7D31-2A3FFC752776">
<createdBy>lpedrero</createdBy>
<createdTime>2020-01-29 17:50:08 UTC</createdTime>
<ownerDesignName>diagrama</ownerDesignName>
</ColumnProxy>
<ColumnProxy name="FI_ID_EMPRESA" id="6622025B-76E0-C2E1-43EF-B12C8FE7306A">
<createdBy>lpedrero</createdBy>
<createdTime>2020-01-29 17:50:08 UTC</createdTime>
<ownerDesignName>diagrama</ownerDesignName>
</ColumnProxy>
<ColumnProxy name="FI_ID_INSTITUCION" id="6B32546D-63CE-B04D-ADF1-DD40318AA13F">
<createdBy>lpedrero</createdBy>
<createdTime>2020-01-29 17:50:08 UTC</createdTime>
<ownerDesignName>diagrama</ownerDesignName>
</ColumnProxy>
<ColumnProxy name="FC_RFC" id="7574FD50-77C9-B314-2CDB-52963032D182">
<createdBy>lpedrero</createdBy>
<createdTime>2020-01-29 17:50:08 UTC</createdTime>
<ownerDesignName>diagrama</ownerDesignName>
</ColumnProxy>
<ColumnProxy name="FI_ID_CTA_FRE_DAZ" id="7F8A3875-4A5D-812B-1368-269A438FC264">
<createdBy>lpedrero</createdBy>
<createdTime>2020-01-29 17:50:08 UTC</createdTime>
<ownerDesignName>diagrama</ownerDesignName>
</ColumnProxy>
<ColumnProxy name="FC_NUMERO_CUENTA" id="8176C400-DBB3-AD1B-95A2-662D18A95955">
<createdBy>lpedrero</createdBy>
<createdTime>2020-01-29 17:50:08 UTC</createdTime>
<ownerDesignName>diagrama</ownerDesignName>
</ColumnProxy>
<ColumnProxy name="FD_FECHA_MODIFICO" id="929E0D04-7CCB-6405-CA0F-81AAEF43EBEA">
<createdBy>lpedrero</createdBy>
<createdTime>2020-01-29 17:50:08 UTC</createdTime>
<ownerDesignName>diagrama</ownerDesignName>
</ColumnProxy>
<ColumnProxy name="FI_ID_CTA_INSTITUCION" id="93E7AB49-B79D-FE89-4317-7D007660A810">
<createdBy>lpedrero</createdBy>
<createdTime>2020-01-29 17:50:08 UTC</createdTime>
<ownerDesignName>diagrama</ownerDesignName>
</ColumnProxy>
<ColumnProxy name="FC_BENEFICIARIO" id="D8728A8C-FB78-D996-A9EB-2601C5689707">
<createdBy>lpedrero</createdBy>
<createdTime>2020-01-29 17:50:08 UTC</createdTime>
<ownerDesignName>diagrama</ownerDesignName>
</ColumnProxy>
<ColumnProxy name="FC_ID_CONTRATO_DAZ" id="E9F15E25-260A-C22F-885E-1A3D3FA3A87E">
<createdBy>lpedrero</createdBy>
<createdTime>2020-01-29 17:50:08 UTC</createdTime>
<ownerDesignName>diagrama</ownerDesignName>
</ColumnProxy>
<ColumnProxy name="FI_ID_FOLIO_IND_BAJA" id="EDB6968F-5A14-BD00-57CB-2677F6F52286">
<createdBy>lpedrero</createdBy>
<createdTime>2020-01-29 17:50:08 UTC</createdTime>
<ownerDesignName>diagrama</ownerDesignName>
</ColumnProxy>
</columnProxies>
<indexProxies>
<IndexProxy class="oracle.dbtools.crest.model.design.storage.oracle.v10g.IndexProxyOraclev10g" name="IX_CTA_FREC_DAZ" id="00D6FE45-175F-9EFE-A290-4644A2B2DECB">
<createdBy>lpedrero</createdBy>
<createdTime>2020-01-29 17:50:08 UTC</createdTime>
<ownerDesignName>diagrama</ownerDesignName>
<schemaObject>8AD07257-1A3E-3202-6080-D8F43B2E5CBC</schemaObject>
<segment>18AE6A20-69DA-500E-E571-74AC0B0777AE</segment>
<tableSpace>05A35985-1D8C-3ACE-B012-015A63E1E0FA</tableSpace>
</IndexProxy>
<IndexProxy class="oracle.dbtools.crest.model.design.storage.oracle.v10g.IndexProxyOraclev10g" name="PK_CTA_FRE_DAZ" id="BE640A1D-048B-7DB2-FB3A-6CDA122170A3">
<createdBy>lpedrero</createdBy>
<createdTime>2020-01-29 17:50:08 UTC</createdTime>
<ownerDesignName>diagrama</ownerDesignName>
<schemaObject>8AD07257-1A3E-3202-6080-D8F43B2E5CBC</schemaObject>
<segment>18AE6A20-69DA-500E-E571-74AC0B0777AE</segment>
<tableSpace>05A35985-1D8C-3ACE-B012-015A63E1E0FA</tableSpace>
</IndexProxy>
</indexProxies>
<primaryKeys>
<PrimaryKey class="oracle.dbtools.crest.model.design.storage.oracle.v10g.PKProxyOraclev10g" name="PK_CTA_FRE_DAZ" id="005C9CCC-C867-EAA7-7DD2-C82EBA76E3FC">
<createdBy>lpedrero</createdBy>
<createdTime>2020-01-29 17:50:08 UTC</createdTime>
<ownerDesignName>diagrama</ownerDesignName>
<segment>18AE6A20-69DA-500E-E571-74AC0B0777AE</segment>
<tableSpace>05A35985-1D8C-3ACE-B012-015A63E1E0FA</tableSpace>
<existingIndex>BE640A1D-048B-7DB2-FB3A-6CDA122170A3</existingIndex>
<indexSegment>18AE6A20-69DA-500E-E571-74AC0B0777AE</indexSegment>
<indexSort>SORTED</indexSort>
<usingIndex>BY INDEX NAME</usingIndex>
</PrimaryKey>
</primaryKeys>
</TableProxyOraclev11g>