<?xml version = '1.0' encoding = 'UTF-8'?>
<TableProxyOraclev11g class="oracle.dbtools.crest.model.design.storage.oracle.v11g.TableProxyOraclev11g" name="TA_RECIBO_CONTR" directorySegmentName="seg_0" id="5D935816-BE7C-B25F-BC06-41FB7BC4D219">
<createdBy>lpedrero</createdBy>
<createdTime>2020-01-29 17:50:08 UTC</createdTime>
<ownerDesignName>diagrama</ownerDesignName>
<schemaObject>8AD07257-1A3E-3202-6080-D8F43B2E5CBC</schemaObject>
<logging>YES</logging>
<partitionedRowMovement>DISABLE</partitionedRowMovement>
<segment>00857EC9-BD8C-A806-AEA6-BD7C8901D8AD</segment>
<tableSpace>650BE115-57FE-CB38-6863-EC17C1BBBCDC</tableSpace>
<temporaryChanged>false</temporaryChanged>
<accessDriverType>oracle_loader</accessDriverType>
<rejectLimit></rejectLimit>
<columnProxies itemClass="oracle.dbtools.crest.model.design.storage.oracle.v12c.ColumnProxyOraclev12c">
<ColumnProxy name="FC_CIUDAD_RESIDENCIA" id="010EE274-D730-1F83-4C58-C47BB0753DD2">
<createdBy>lpedrero</createdBy>
<createdTime>2020-01-29 17:50:08 UTC</createdTime>
<ownerDesignName>diagrama</ownerDesignName>
</ColumnProxy>
<ColumnProxy name="FC_CURP" id="14B1580E-0B1E-F45E-038B-0A37B5722C11">
<createdBy>lpedrero</createdBy>
<createdTime>2020-01-29 17:50:08 UTC</createdTime>
<ownerDesignName>diagrama</ownerDesignName>
</ColumnProxy>
<ColumnProxy name="FC_NUM_INT" id="25586974-666F-7AF1-9717-7967DBB65CC3">
<createdBy>lpedrero</createdBy>
<createdTime>2020-01-29 17:50:08 UTC</createdTime>
<ownerDesignName>diagrama</ownerDesignName>
</ColumnProxy>
<ColumnProxy name="FC_CALLE" id="2AC8F750-37A1-4A12-DF24-538317520702">
<createdBy>lpedrero</createdBy>
<createdTime>2020-01-29 17:50:08 UTC</createdTime>
<ownerDesignName>diagrama</ownerDesignName>
</ColumnProxy>
<ColumnProxy name="FC_NUMERO_DETALLE" id="2F1B84A4-B90D-9C32-9A41-92DB78C1BC57">
<createdBy>lpedrero</createdBy>
<createdTime>2020-01-29 17:50:08 UTC</createdTime>
<ownerDesignName>diagrama</ownerDesignName>
</ColumnProxy>
<ColumnProxy name="FC_USUARIO_MODIFICO" id="43F4F7D8-7952-DB39-FC3E-D599963E1903">
<createdBy>lpedrero</createdBy>
<createdTime>2020-01-29 17:50:08 UTC</createdTime>
<ownerDesignName>diagrama</ownerDesignName>
<defaultValue>&apos;EMPRESARIO&apos;</defaultValue>
</ColumnProxy>
<ColumnProxy name="FI_NUM_IDENT" id="4E24AC4C-E5C9-8F47-8E9A-2164A662DFF7">
<createdBy>lpedrero</createdBy>
<createdTime>2020-01-29 17:50:08 UTC</createdTime>
<ownerDesignName>diagrama</ownerDesignName>
</ColumnProxy>
<ColumnProxy name="FD_FECHA_ALTA" id="539D2AE7-D49B-2A4B-DBEB-95D0AFCE9569">
<createdBy>lpedrero</createdBy>
<createdTime>2020-01-29 17:50:08 UTC</createdTime>
<ownerDesignName>diagrama</ownerDesignName>
</ColumnProxy>
<ColumnProxy name="FC_USUARIO_ALTA" id="5F62CABC-2784-09C5-3DE6-68BA58716EBF">
<createdBy>lpedrero</createdBy>
<createdTime>2020-01-29 17:50:08 UTC</createdTime>
<ownerDesignName>diagrama</ownerDesignName>
</ColumnProxy>
<ColumnProxy name="FC_CIUDAD_LABORAL" id="5F6A4E23-6FF6-6B91-C868-2A66E784DF4A">
<createdBy>lpedrero</createdBy>
<createdTime>2020-01-29 17:50:08 UTC</createdTime>
<ownerDesignName>diagrama</ownerDesignName>
</ColumnProxy>
<ColumnProxy name="FC_CODIGO_POSTAL" id="6A6A3342-C24A-9323-AE02-813E67713260">
<createdBy>lpedrero</createdBy>
<createdTime>2020-01-29 17:50:08 UTC</createdTime>
<ownerDesignName>diagrama</ownerDesignName>
</ColumnProxy>
<ColumnProxy name="FC_LLAVE" id="71FC21B4-108D-FC30-0210-2A645F803EA5">
<createdBy>lpedrero</createdBy>
<createdTime>2020-01-29 17:50:08 UTC</createdTime>
<ownerDesignName>diagrama</ownerDesignName>
</ColumnProxy>
<ColumnProxy name="FC_FECHA_VIGENCIA" id="96AB5142-55C6-10E6-2C20-5F6BFB2A4DF4">
<createdBy>lpedrero</createdBy>
<createdTime>2020-01-29 17:50:08 UTC</createdTime>
<ownerDesignName>diagrama</ownerDesignName>
</ColumnProxy>
<ColumnProxy name="FI_STATUS" id="9758A973-834A-C1CF-BF0A-E80FDBDE9197">
<createdBy>lpedrero</createdBy>
<createdTime>2020-01-29 17:50:08 UTC</createdTime>
<ownerDesignName>diagrama</ownerDesignName>
</ColumnProxy>
<ColumnProxy name="FC_ESTADO" id="99552D16-8DEB-7577-672D-12F174DD7DE6">
<createdBy>lpedrero</createdBy>
<createdTime>2020-01-29 17:50:08 UTC</createdTime>
<ownerDesignName>diagrama</ownerDesignName>
</ColumnProxy>
<ColumnProxy name="FI_ID_FOLIO" id="B2A1A170-FF8B-A6AD-60AE-1797DA85E563">
<createdBy>lpedrero</createdBy>
<createdTime>2020-01-29 17:50:08 UTC</createdTime>
<ownerDesignName>diagrama</ownerDesignName>
</ColumnProxy>
<ColumnProxy name="FD_FECHA_MODIFICO" id="B85D0797-6633-2477-A08D-33A7B922270E">
<createdBy>lpedrero</createdBy>
<createdTime>2020-01-29 17:50:08 UTC</createdTime>
<ownerDesignName>diagrama</ownerDesignName>
<defaultValue>SYSDATE</defaultValue>
</ColumnProxy>
<ColumnProxy name="FC_TIPO_REGISTRO" id="BD0928F5-3345-5A08-7F77-06684F45A42B">
<createdBy>lpedrero</createdBy>
<createdTime>2020-01-29 17:50:08 UTC</createdTime>
<ownerDesignName>diagrama</ownerDesignName>
</ColumnProxy>
<ColumnProxy name="FC_COLONIA" id="CC1CC693-AF4D-3C4E-6AFC-3FEDCDDEA7F5">
<createdBy>lpedrero</createdBy>
<createdTime>2020-01-29 17:50:08 UTC</createdTime>
<ownerDesignName>diagrama</ownerDesignName>
</ColumnProxy>
<ColumnProxy name="FC_NUM_EXT" id="DA3B3015-927E-1936-7132-BF7899B8B236">
<createdBy>lpedrero</createdBy>
<createdTime>2020-01-29 17:50:08 UTC</createdTime>
<ownerDesignName>diagrama</ownerDesignName>
</ColumnProxy>
<ColumnProxy name="FC_ID_PLANTILLA" id="DA4BB562-0ED5-2911-82CA-E9E92B62A3CA">
<createdBy>lpedrero</createdBy>
<createdTime>2020-01-29 17:50:08 UTC</createdTime>
<ownerDesignName>diagrama</ownerDesignName>
</ColumnProxy>
<ColumnProxy name="FC_PAIS" id="E683176C-54C5-DE61-F064-5A4EA9A3E6D4">
<createdBy>lpedrero</createdBy>
<createdTime>2020-01-29 17:50:08 UTC</createdTime>
<ownerDesignName>diagrama</ownerDesignName>
</ColumnProxy>
<ColumnProxy name="FC_NUMERO_CONTRATO" id="E6E581B5-75DF-3D23-FD76-58FEF67C3BB2">
<createdBy>lpedrero</createdBy>
<createdTime>2020-01-29 17:50:08 UTC</createdTime>
<ownerDesignName>diagrama</ownerDesignName>
</ColumnProxy>
</columnProxies>
<indexProxies>
<IndexProxy class="oracle.dbtools.crest.model.design.storage.oracle.v10g.IndexProxyOraclev10g" name="PK_CONTRATO_REC" id="91F68CB0-3A88-61A0-5BC7-FB0096E569C3">
<createdBy>lpedrero</createdBy>
<createdTime>2020-01-29 17:50:08 UTC</createdTime>
<ownerDesignName>diagrama</ownerDesignName>
<schemaObject>8AD07257-1A3E-3202-6080-D8F43B2E5CBC</schemaObject>
<segment>D42CBA5B-2CEA-C3FB-46CA-6CC1D4E60E4B</segment>
<tableSpace>E541B2BF-D89F-DF93-0392-5DD230274D78</tableSpace>
</IndexProxy>
</indexProxies>
<primaryKeys>
<PrimaryKey class="oracle.dbtools.crest.model.design.storage.oracle.v10g.PKProxyOraclev10g" name="PK_CONTRATO_REC" id="7A82BAE3-9D91-1711-FDAC-711FEDAF0277">
<createdBy>lpedrero</createdBy>
<createdTime>2020-01-29 17:50:08 UTC</createdTime>
<ownerDesignName>diagrama</ownerDesignName>
<segment>D42CBA5B-2CEA-C3FB-46CA-6CC1D4E60E4B</segment>
<tableSpace>E541B2BF-D89F-DF93-0392-5DD230274D78</tableSpace>
<existingIndex>91F68CB0-3A88-61A0-5BC7-FB0096E569C3</existingIndex>
<indexSegment>D42CBA5B-2CEA-C3FB-46CA-6CC1D4E60E4B</indexSegment>
<indexSort>SORTED</indexSort>
<usingIndex>BY INDEX NAME</usingIndex>
</PrimaryKey>
</primaryKeys>
</TableProxyOraclev11g>