<?xml version = '1.0' encoding = 'UTF-8'?>
<TableProxyOraclev11g class="oracle.dbtools.crest.model.design.storage.oracle.v11g.TableProxyOraclev11g" name="TA_SOL_RECE_TAR" directorySegmentName="seg_0" id="F8ECAF51-4B1E-0032-5342-6D25D92A0FF5">
<createdBy>lpedrero</createdBy>
<createdTime>2020-01-29 17:50:08 UTC</createdTime>
<ownerDesignName>diagrama</ownerDesignName>
<schemaObject>8AD07257-1A3E-3202-6080-D8F43B2E5CBC</schemaObject>
<logging>YES</logging>
<partitionedRowMovement>DISABLE</partitionedRowMovement>
<segment>00857EC9-BD8C-A806-AEA6-BD7C8901D8AD</segment>
<tableSpace>650BE115-57FE-CB38-6863-EC17C1BBBCDC</tableSpace>
<temporaryChanged>false</temporaryChanged>
<accessDriverType>oracle_loader</accessDriverType>
<rejectLimit></rejectLimit>
<columnProxies itemClass="oracle.dbtools.crest.model.design.storage.oracle.v12c.ColumnProxyOraclev12c">
<ColumnProxy name="FC_TIPO_PRODUC" id="19DC4D63-24D8-61EB-37CF-4F7D76C4BF3B">
<createdBy>lpedrero</createdBy>
<createdTime>2020-01-29 17:50:08 UTC</createdTime>
<ownerDesignName>diagrama</ownerDesignName>
</ColumnProxy>
<ColumnProxy name="FI_NUM_TARJ_RECI" id="25FE2202-6AFF-8C32-76DE-D785901EA81B">
<createdBy>lpedrero</createdBy>
<createdTime>2020-01-29 17:50:08 UTC</createdTime>
<ownerDesignName>diagrama</ownerDesignName>
</ColumnProxy>
<ColumnProxy name="FI_ID_FOLIO" id="437DF047-DEC1-9047-F88D-A7BCC4B539D4">
<createdBy>lpedrero</createdBy>
<createdTime>2020-01-29 17:50:08 UTC</createdTime>
<ownerDesignName>diagrama</ownerDesignName>
</ColumnProxy>
<ColumnProxy name="FC_LOTE" id="44397743-39D7-5D33-A513-6741864AEF0E">
<createdBy>lpedrero</createdBy>
<createdTime>2020-01-29 17:50:08 UTC</createdTime>
<ownerDesignName>diagrama</ownerDesignName>
</ColumnProxy>
<ColumnProxy name="FD_FECHA_ALTA" id="4EE4BC67-3296-56A9-1A9D-9F01D6F3B35B">
<createdBy>lpedrero</createdBy>
<createdTime>2020-01-29 17:50:08 UTC</createdTime>
<ownerDesignName>diagrama</ownerDesignName>
</ColumnProxy>
<ColumnProxy name="FI_NUM_TARJ_GUIA" id="52B1F298-DD30-761B-901A-C9DD5EF3293E">
<createdBy>lpedrero</createdBy>
<createdTime>2020-01-29 17:50:08 UTC</createdTime>
<ownerDesignName>diagrama</ownerDesignName>
</ColumnProxy>
<ColumnProxy name="FI_STATUS" id="5F28C6C5-A7A8-E7C0-5D67-6DAF7B5689EE">
<createdBy>lpedrero</createdBy>
<createdTime>2020-01-29 17:50:08 UTC</createdTime>
<ownerDesignName>diagrama</ownerDesignName>
</ColumnProxy>
<ColumnProxy name="FD_FECHA_RECEP" id="72C0189B-C070-A477-B670-B4610E580A9E">
<createdBy>lpedrero</createdBy>
<createdTime>2020-01-29 17:50:08 UTC</createdTime>
<ownerDesignName>diagrama</ownerDesignName>
</ColumnProxy>
<ColumnProxy name="FC_NUM_GUIA" id="816B3678-A96E-81E9-9A28-3EAC4716EFFA">
<createdBy>lpedrero</createdBy>
<createdTime>2020-01-29 17:50:08 UTC</createdTime>
<ownerDesignName>diagrama</ownerDesignName>
</ColumnProxy>
<ColumnProxy name="FC_FOLIO_TRANS" id="8EE1CF76-2331-ECE1-3C96-75D4FCD243C5">
<createdBy>lpedrero</createdBy>
<createdTime>2020-01-29 17:50:08 UTC</createdTime>
<ownerDesignName>diagrama</ownerDesignName>
</ColumnProxy>
<ColumnProxy name="FC_USUARIO_MODIFICO" id="CFF929CD-072D-2E67-7035-4FA7DA925054">
<createdBy>lpedrero</createdBy>
<createdTime>2020-01-29 17:50:08 UTC</createdTime>
<ownerDesignName>diagrama</ownerDesignName>
</ColumnProxy>
<ColumnProxy name="FD_FECHA_MODIFICO" id="E7EF8EEE-521F-1C17-09ED-266DFBEF951A">
<createdBy>lpedrero</createdBy>
<createdTime>2020-01-29 17:50:08 UTC</createdTime>
<ownerDesignName>diagrama</ownerDesignName>
</ColumnProxy>
<ColumnProxy name="FC_USUARIO_ALTA" id="FF5518F9-1C66-8CF6-B8F7-7F692450C87D">
<createdBy>lpedrero</createdBy>
<createdTime>2020-01-29 17:50:08 UTC</createdTime>
<ownerDesignName>diagrama</ownerDesignName>
</ColumnProxy>
</columnProxies>
<indexProxies>
<IndexProxy class="oracle.dbtools.crest.model.design.storage.oracle.v10g.IndexProxyOraclev10g" name="PK_RECEP_TAR" id="A488CDE6-8CAE-9125-E1F7-E54B80F3A7A9">
<createdBy>lpedrero</createdBy>
<createdTime>2020-01-29 17:50:08 UTC</createdTime>
<ownerDesignName>diagrama</ownerDesignName>
<schemaObject>8AD07257-1A3E-3202-6080-D8F43B2E5CBC</schemaObject>
<logging>NO</logging>
<segment>D42CBA5B-2CEA-C3FB-46CA-6CC1D4E60E4B</segment>
<tableSpace>E541B2BF-D89F-DF93-0392-5DD230274D78</tableSpace>
</IndexProxy>
</indexProxies>
<foreignKeys>
<ForeignKey class="oracle.dbtools.crest.model.design.storage.oracle.v10g.FKProxyOraclev10g" name="FK_RECEP_FOL" id="FBCA7FB3-D5D0-8D95-D066-830C5BE32226">
<createdBy>lpedrero</createdBy>
<createdTime>2020-01-29 17:50:09 UTC</createdTime>
<ownerDesignName>diagrama</ownerDesignName>
</ForeignKey>
</foreignKeys>
<primaryKeys>
<PrimaryKey class="oracle.dbtools.crest.model.design.storage.oracle.v10g.PKProxyOraclev10g" name="PK_RECEP_TAR" id="7F77AAAD-3B5A-A36C-8164-486DAE527C62">
<createdBy>lpedrero</createdBy>
<createdTime>2020-01-29 17:50:08 UTC</createdTime>
<ownerDesignName>diagrama</ownerDesignName>
<logging>NO</logging>
<segment>D42CBA5B-2CEA-C3FB-46CA-6CC1D4E60E4B</segment>
<tableSpace>E541B2BF-D89F-DF93-0392-5DD230274D78</tableSpace>
<existingIndex>A488CDE6-8CAE-9125-E1F7-E54B80F3A7A9</existingIndex>
<indexSegment>D42CBA5B-2CEA-C3FB-46CA-6CC1D4E60E4B</indexSegment>
<indexSort>SORTED</indexSort>
<usingIndex>BY INDEX NAME</usingIndex>
</PrimaryKey>
</primaryKeys>
</TableProxyOraclev11g>